fart/__init__.py
fart/clipper.py
fart/fart.py
fart/fonts/__init__.py
fart/fonts/alpha.py
fart/fonts/ansi_regular.py
fart/fonts/ansi_shadow.py
fart/fonts/banner.py
fart/fonts/banner3.py
fart/fonts/big.py
fart/fonts/colossal.py
fart/fonts/georgia11.py
fart/fonts/impossible.py
fart/fonts/isometric1.py
fart/fonts/isometric2.py
fart/fonts/isometric3.py
fart/fonts/isometric4.py
fart/fonts/larry_3d.py
fart/fonts/max4.py
fart/fonts/modular.py
fart/fonts/nancyj.py
fart/fonts/nscript.py
fart/fonts/roman.py
fart/fonts/slant.py
fart/fonts/slant_relief.py
fart/fonts/small.py
fart/fonts/small_slant.py
fart/fonts/standard.py
fart/fonts/stick_letters.py
fart/fonts/univers.py
fart/fonts/usa_flag.py
fart-0.2.3.dist-info/LICENSE
fart-0.2.3.dist-info/METADATA
fart-0.2.3.dist-info/WHEEL
fart-0.2.3.dist-info/entry_points.txt
fart-0.2.3.dist-info/top_level.txt
fart-0.2.3.dist-info/RECORD
