Metadata-Version: 2.1
Name: fart
Version: 0.2.3
Summary: Fart all over your documentation
Author-email: Evan Cushing <evdcush@protonmail.com>
License: BSD 3-Clause License
Project-URL: Homepage, https://github.com/evdcush/fart
Classifier: License :: OSI Approved :: BSD License
Classifier: Programming Language :: Python
Classifier: Programming Language :: Python :: 2
Classifier: Programming Language :: Python :: 2.7
Classifier: Programming Language :: Python :: 3
Classifier: Programming Language :: Python :: 3.4
Classifier: Programming Language :: Python :: 3.5
Classifier: Programming Language :: Python :: 3.6
Classifier: Programming Language :: Python :: 3.7
License-File: LICENSE
